simple/__init__.py
simple/functions.py
simpleton/__init__.py
simpleton/functions.py
Simpleton-1.0.0.dist-info/LICENSE
Simpleton-1.0.0.dist-info/METADATA
Simpleton-1.0.0.dist-info/WHEEL
Simpleton-1.0.0.dist-info/top_level.txt
Simpleton-1.0.0.dist-info/zip-safe
Simpleton-1.0.0.dist-info/RECORD
