Metadata-Version: 2.1
Name: Simpleton
Version: 1.0.0
Summary: Imports commonly used standard-library modules.
Home-page: https://github.com/c00lhawk607/simpleton
Author: Jordan Dixon
Author-email: jordandixon2004@outlook.com
License: GNU General Public License v3 (GPLv3)
Platform: UNKNOWN
Classifier: Programming Language :: Python :: 3
Classifier: License :: OSI Approved :: GNU General Public License v3 (GPLv3)
Classifier: Operating System :: OS Independent
Classifier: Development Status :: 5 - Production/Stable
Classifier: Intended Audience :: Developers
Classifier: Natural Language :: English
Classifier: Topic :: Software Development :: Build Tools
Classifier: Topic :: Utilities
Requires-Python: >=3.0
